langchain_notion_tools/__init__.py
langchain_notion_tools/blocks.py
langchain_notion_tools/cli.py
langchain_notion_tools/client.py
langchain_notion_tools/config.py
langchain_notion_tools/exceptions.py
langchain_notion_tools/toolkit.py
langchain_notion_tools/tools/__init__.py
langchain_notion_tools/tools/search.py
langchain_notion_tools/tools/write.py
langchain_notion_tools-0.1.0.dist-info/METADATA
langchain_notion_tools-0.1.0.dist-info/WHEEL
langchain_notion_tools-0.1.0.dist-info/entry_points.txt
langchain_notion_tools-0.1.0.dist-info/licenses/LICENSE
langchain_notion_tools-0.1.0.dist-info/RECORD
