Metadata-Version: 2.4
Name: langchain-notion-tools
Version: 0.1.0
Summary: LangChain tools for read/write access to Notion via the official API.
Project-URL: Homepage, https://github.com/dineshkumarkummara/langchain-notion-tool
Project-URL: Repository, https://github.com/dineshkumarkummara/langchain-notion-tool
Project-URL: Bug Tracker, https://github.com/dineshkumarkummara/langchain-notion-tool/issues
Author: Dinesh
License: MIT
License-File: LICENSE
Keywords: agents,langchain,llm,notion
Classifier: Development Status :: 1 - Planning
Classifier: Intended Audience :: Developers
Classifier: License :: OSI Approved :: MIT License
Classifier: Programming Language :: Python
Classifier: Programming Language :: Python :: 3
Classifier: Programming Language :: Python :: 3.9
Classifier: Programming Language :: Python :: 3.10
Classifier: Programming Language :: Python :: 3.11
Classifier: Programming Language :: Python :: 3.12
Classifier: Topic :: Software Development :: Libraries :: Python Modules
Requires-Python: >=3.9
Requires-Dist: anyio
Requires-Dist: httpx
Requires-Dist: langchain-core>=0.3
Requires-Dist: notion-client>=2
Requires-Dist: pydantic>=2
Requires-Dist: typing-extensions
Provides-Extra: dev
Requires-Dist: build; extra == 'dev'
Requires-Dist: hypothesis; extra == 'dev'
Requires-Dist: mkdocs; extra == 'dev'
Requires-Dist: mkdocs-material; extra == 'dev'
Requires-Dist: mkdocstrings[python]; extra == 'dev'
Requires-Dist: mypy; extra == 'dev'
Requires-Dist: pytest; extra == 'dev'
Requires-Dist: pytest-asyncio; extra == 'dev'
Requires-Dist: pytest-cov; extra == 'dev'
Requires-Dist: python-semantic-release; extra == 'dev'
Requires-Dist: ruff; extra == 'dev'
Requires-Dist: twine; extra == 'dev'
